qusource/__init__.py
qusource/calculation.py
qusource/circuit.py
qusource/gate.py
qusource/measurement.py
qusource/qusource.py
qusource/unitary.py
qusource/utils.py
qusource-0.0.4.dist-info/LICENSE
qusource-0.0.4.dist-info/METADATA
qusource-0.0.4.dist-info/WHEEL
qusource-0.0.4.dist-info/top_level.txt
qusource-0.0.4.dist-info/RECORD
